.travis.yml
MANIFEST.in
README.rst
dev-requirements.txt
setup.py
tox.ini
currencycloud/__init__.py
currencycloud/config.py
currencycloud/pagination.py
currencycloud/request_handler.py
currencycloud/resource.py
currencycloud/resourceful_collection.py
currencycloud/response_handler.py
currencycloud/session.py
currencycloud/utilities.py
currencycloud/version.py
currencycloud.egg-info/PKG-INFO
currencycloud.egg-info/SOURCES.txt
currencycloud.egg-info/dependency_links.txt
currencycloud.egg-info/requires.txt
currencycloud.egg-info/top_level.txt
currencycloud/actions/__init__.py
currencycloud/actions/create.py
currencycloud/actions/current.py
currencycloud/actions/delete.py
currencycloud/actions/find.py
currencycloud/actions/retrieve.py
currencycloud/actions/save.py
currencycloud/actions/update.py
currencycloud/errors/__init__.py
currencycloud/errors/api.py
currencycloud/errors/general.py
currencycloud/errors/unexpected.py
currencycloud/resources/__init__.py
currencycloud/resources/account.py
currencycloud/resources/balance.py
currencycloud/resources/beneficiary.py
currencycloud/resources/contact.py
currencycloud/resources/conversion.py
currencycloud/resources/payer.py
currencycloud/resources/payment.py
currencycloud/resources/rate.py
currencycloud/resources/reference.py
currencycloud/resources/settlement.py
currencycloud/resources/transaction.py
examples/server.py
test/conftest.py
test/conftest.pyc
test/currency_cloud/test_currencycloud.py
test/currency_cloud/test_request_handler.py
test/currency_cloud/test_resource.py
test/fixtures/vcr_cassettes/actions/can_create.json
test/fixtures/vcr_cassettes/actions/can_current.json
test/fixtures/vcr_cassettes/actions/can_delete.json
test/fixtures/vcr_cassettes/actions/can_find.json
test/fixtures/vcr_cassettes/actions/can_first.json
test/fixtures/vcr_cassettes/actions/can_retrieve.json
test/fixtures/vcr_cassettes/actions/can_update.json
test/fixtures/vcr_cassettes/actions/can_use_currency_to_retrieve_balance.json
test/fixtures/vcr_cassettes/actions/can_validate_beneficiaries.json
test/fixtures/vcr_cassettes/authentication/can_be_closed.json
test/fixtures/vcr_cassettes/authentication/can_use_just_a_token.json
