Metadata-Version: 1.1
Name: currencycloud
Version: 0.7.0
Summary: Python SDK for the Currency Cloud API.
Home-page: https://connect.currencycloud.com/documentation/getting-started/introduction
Author: Alessandro Iob
Author-email: alessandro.iob@toptal.com
License: MIT
Keywords: urllib httplib threadsafe filepost http https ssl pooling
Platform: UNKNOWN
Classifier: Development Status :: 2 - Pre-Alpha
Classifier: Intended Audience :: Developers
Classifier: License :: OSI Approved :: MIT License
Classifier: Operating System :: OS Independent
Classifier: Programming Language :: Python
Classifier: Programming Language :: Python :: 2
Classifier: Programming Language :: Python :: 2.6
Classifier: Programming Language :: Python :: 2.7
Classifier: Programming Language :: Python :: 3
Classifier: Programming Language :: Python :: 3.2
Classifier: Programming Language :: Python :: 3.3
Classifier: Programming Language :: Python :: 3.4
Classifier: Programming Language :: Python :: Implementation :: PyPy
Classifier: Topic :: Software Development :: Libraries :: Python Modules
